library/__init__.py
library/code_comparison/__init__.py
library/code_comparison/avanessova_diss/cables/__init__.py
library/code_comparison/avanessova_diss/cables/array_cable.yaml
library/code_comparison/avanessova_diss/cables/array_cable_increase_failure.yaml
library/code_comparison/avanessova_diss/cables/array_cable_increase_maintenance.yaml
library/code_comparison/avanessova_diss/cables/array_cable_no_major.yaml
library/code_comparison/avanessova_diss/cables/export_cable.yaml
library/code_comparison/avanessova_diss/project/config/__init__.py
library/code_comparison/avanessova_diss/project/config/fixed_costs.yaml
library/code_comparison/avanessova_diss/project/config/layout_1_in_situ_base.yaml
library/code_comparison/avanessova_diss/project/config/layout_1_in_situ_base_24hr.yaml
library/code_comparison/avanessova_diss/project/config/layout_1_in_situ_base_copy.yaml
library/code_comparison/avanessova_diss/project/config/layout_1_in_situ_increase_failure.yaml
library/code_comparison/avanessova_diss/project/config/layout_1_in_situ_increase_failure_24hr.yaml
library/code_comparison/avanessova_diss/project/config/layout_1_in_situ_increase_maintenance.yaml
library/code_comparison/avanessova_diss/project/config/layout_1_in_situ_increase_wave.yaml
library/code_comparison/avanessova_diss/project/config/layout_1_in_situ_no_major.yaml
library/code_comparison/avanessova_diss/project/config/layout_1_tow_base.yaml
library/code_comparison/avanessova_diss/project/config/layout_1_tow_base_24hr.yaml
library/code_comparison/avanessova_diss/project/config/layout_1_tow_increase_failure.yaml
library/code_comparison/avanessova_diss/project/config/layout_1_tow_increase_maintenance.yaml
library/code_comparison/avanessova_diss/project/config/layout_1_tow_increase_wave.yaml
library/code_comparison/avanessova_diss/project/config/layout_2_in_situ_base.yaml
library/code_comparison/avanessova_diss/project/config/layout_2_tow_base.yaml
wombat-0.13.1.dist-info/licenses/LICENSE
wombat-0.13.1.dist-info/licenses/NOTICE
wombat-0.13.1.dist-info/METADATA
wombat-0.13.1.dist-info/WHEEL
wombat-0.13.1.dist-info/top_level.txt
wombat-0.13.1.dist-info/RECORD
