Metadata-Version: 2.4
Name: wombat
Version: 0.13.1
Summary: Windfarm operations and maintenance cost-benefit analysis tool
Author-email: Rob Hammond <rob.hammond@nrel.gov>
License:                                  Apache License
Project-URL: source, https://github.com/WISDEM/WOMBAT
Project-URL: documentation, https://wisdem.github.io/WOMBAT/
Project-URL: issues, https://github.com/WISDEM/WOMBAT/issues
Project-URL: changelog, https://github.com/WISDEM/WOMBAT/blob/main/CHANGELOG.md
Keywords: python3,wind-energy,operations-maintenance,discrete-event-simulation,simulation
Classifier: Development Status :: 4 - Beta
Classifier: Intended Audience :: Developers
Classifier: Intended Audience :: Science/Research
Classifier: Intended Audience :: Other Audience
Classifier: License :: OSI Approved :: Apache Software License
Classifier: Natural Language :: English
Classifier: Operating System :: OS Independent
Classifier: Programming Language :: Python
Classifier: Programming Language :: Python :: 3 :: Only
Classifier: Programming Language :: Python :: 3.10
Classifier: Programming Language :: Python :: 3.11
Classifier: Programming Language :: Python :: 3.12
Classifier: Programming Language :: Python :: 3.13
Classifier: Programming Language :: Python :: 3.14
Classifier: Topic :: Scientific/Engineering
Classifier: Topic :: Software Development :: Libraries :: Python Modules
Classifier: Typing :: Typed
Requires-Python: >=3.11
License-File: LICENSE
License-File: NOTICE
Requires-Dist: attrs>=24.1.0
Requires-Dist: numpy>=1.21
Requires-Dist: scipy>=1.8
Requires-Dist: pandas>=2
Requires-Dist: polars>=1.33.1
Requires-Dist: pyarrow>=10
Requires-Dist: jupyterlab>=3
Requires-Dist: simpy>=4.0.1
Requires-Dist: pyyaml>=6
Requires-Dist: geopy>=2.3
Requires-Dist: networkx>=2.7
Requires-Dist: matplotlib>=3.3
Requires-Dist: types-attrs>=19
Requires-Dist: types-typed-ast>=1.5
Requires-Dist: types-PyYAML>=6
Requires-Dist: types-python-dateutil>=2.8
Requires-Dist: python-dateutil
Requires-Dist: polars-lts-cpu; sys_platform == "darwin"
Provides-Extra: dev
Requires-Dist: pre-commit>=2.20; extra == "dev"
Requires-Dist: isort>=5.10; extra == "dev"
Requires-Dist: pytest>=7; extra == "dev"
Requires-Dist: pytest-cov>=4; extra == "dev"
Requires-Dist: pytest-check; extra == "dev"
Requires-Dist: mypy; extra == "dev"
Requires-Dist: ruff>=0.2; extra == "dev"
Requires-Dist: pyupgrade; extra == "dev"
Provides-Extra: docs
Requires-Dist: jupyter-book<2,>=1; extra == "docs"
Requires-Dist: myst-nb>=0.16; extra == "docs"
Requires-Dist: myst-parser>=0.17; extra == "docs"
Requires-Dist: linkify-it-py>=2; extra == "docs"
Requires-Dist: sphinx-autodoc-typehints; extra == "docs"
Requires-Dist: sphinxcontrib-autoyaml; extra == "docs"
Requires-Dist: sphinxcontrib-bibtex>=2.4; extra == "docs"
Requires-Dist: sphinxcontrib-spelling>=7; extra == "docs"
Provides-Extra: all
Requires-Dist: wombat[dev,docs]; extra == "all"
Dynamic: license-file
